thalassa/__init__.py
thalassa/api.py
thalassa/api.py.orig
thalassa/normalization.py
thalassa/plotting.py
thalassa/utils.py
thalassa-0.4.5.dist-info/LICENSE
thalassa-0.4.5.dist-info/METADATA
thalassa-0.4.5.dist-info/WHEEL
thalassa-0.4.5.dist-info/RECORD
