Metadata-Version: 2.1
Name: thalassa
Version: 0.4.5
Summary: A library for visualizing large scale results of hydrodynamic simulations
Home-page: https://github.com/ec-jrc/thalassa.git
License: EUPL-1.2
Author: Panos Mavrogiorgos
Author-email: pmav99@gmail.com
Requires-Python: >=3.9,<4.0
Classifier: Development Status :: 4 - Beta
Classifier: Environment :: Other Environment
Classifier: Intended Audience :: Developers
Classifier: Intended Audience :: Science/Research
Classifier: License :: OSI Approved :: European Union Public Licence 1.2 (EUPL 1.2)
Classifier: Operating System :: OS Independent
Classifier: Programming Language :: Python
Classifier: Programming Language :: Python :: 3
Classifier: Programming Language :: Python :: 3.9
Classifier: Programming Language :: Python :: 3.10
Classifier: Programming Language :: Python :: 3.11
Classifier: Programming Language :: Python :: 3.12
Classifier: Topic :: Scientific/Engineering :: GIS
Classifier: Topic :: Scientific/Engineering :: Visualization
Requires-Dist: Cartopy
Requires-Dist: bokeh (>=3.0)
Requires-Dist: dask[array,complete,dataframe,diagnostics,distributed]
Requires-Dist: datashader
Requires-Dist: geopandas
Requires-Dist: geoviews (>=1.10)
Requires-Dist: holoviews (!=1.18.2)
Requires-Dist: numba (>0.52)
Requires-Dist: numpy
Requires-Dist: numpy-indexed
Requires-Dist: pandas
Requires-Dist: pyproj
Requires-Dist: scipy
Requires-Dist: shapely
Requires-Dist: xarray[accel,io]
Project-URL: Repository, https://github.com/ec-jrc/thalassa.git
